Metadata-Version: 2.1
Name: commit-helper
Version: 3.4.18
Summary: A python program that helps you write commits following commit conventions
Home-page: https://github.com/andre-filho/commit-helper
Author: Andre de Sousa Costa Filho
Author-email: andre.filho001@outlook.com
License: GNU
Keywords: commit,helper,git,version,versioning
Platform: UNKNOWN
Classifier: Development Status :: 5 - Production/Stable
Classifier: Intended Audience :: Developers
Classifier: Natural Language :: Portuguese
Classifier: License :: OSI Approved :: GNU General Public License v3 or later (GPLv3+)
Classifier: Operating System :: OS Independent
Classifier: Programming Language :: Python
Classifier: Programming Language :: Python :: 3.6
Classifier: Programming Language :: Python :: Implementation :: CPython
Classifier: Programming Language :: Python :: Implementation :: PyPy
Classifier: Topic :: Software Development :: Libraries :: Python Modules
Requires-Dist: colorama (>=0.4.1)
Requires-Dist: colored (>=1.3.93)
Requires-Dist: pyyaml (>=4.2b1)
Requires-Dist: argparse (>=1.2.0)
